solace_otel/__init__.py
solace_otel/messaging/__init__.py
solace_otel/messaging/trace/__init__.py
solace_otel/messaging/trace/propagation/__init__.py
solace_otel/messaging/trace/propagation/_common.py
solace_otel/messaging/trace/propagation/_inbound_message_carrier.py
solace_otel/messaging/trace/propagation/_inbound_message_getter.py
solace_otel/messaging/trace/propagation/_logging.py
solace_otel/messaging/trace/propagation/_outbound_message_carrier.py
solace_otel/messaging/trace/propagation/_outbound_message_getter.py
solace_otel/messaging/trace/propagation/_outbound_message_setter.py
pubsubplus_opentelemetry_integration-1.0.1.dist-info/LICENSE.txt
pubsubplus_opentelemetry_integration-1.0.1.dist-info/METADATA
pubsubplus_opentelemetry_integration-1.0.1.dist-info/WHEEL
pubsubplus_opentelemetry_integration-1.0.1.dist-info/RECORD
