Metadata-Version: 2.1
Name: pubsubplus-opentelemetry-integration
Version: 1.0.1
Summary: Solace PubSub+ OpenTelemetry Integration API for Python.
License: LICENSE.txt
Author: Solace
Author-email: support@solace.com
Requires-Python: >=3.8,<4.0
Classifier: License :: Other/Proprietary License
Classifier: Programming Language :: Python :: 3
Classifier: Programming Language :: Python :: 3.8
Classifier: Programming Language :: Python :: 3.9
Classifier: Programming Language :: Python :: 3.10
Classifier: Programming Language :: Python :: 3.11
Classifier: Programming Language :: Python :: 3.12
Requires-Dist: opentelemetry-api (==1.22.0)
Requires-Dist: solace-pubsubplus (>=1.7.0,<2.0.0)
